{
  "delta_source": "delta_audit_2026_latest.csv",
  "risers": [
    {
      "player_name": "Brenen Thompson",
      "position": "WR",
      "school": "Mississippi State Bulldogs",
      "rank_delta_prev_minus_curr": 15,
      "top_driver": "athletic (up 0.00)"
    },
    {
      "player_name": "Justin Joly",
      "position": "TE",
      "school": "North Carolina State Wolfpack",
      "rank_delta_prev_minus_curr": 10,
      "top_driver": "athletic (up 0.00)"
    },
    {
      "player_name": "Malachi Fields",
      "position": "WR",
      "school": "Notre Dame Fighting Irish",
      "rank_delta_prev_minus_curr": 10,
      "top_driver": "athletic (up 0.00)"
    },
    {
      "player_name": "Demond Claiborne",
      "position": "RB",
      "school": "Wake Forest Demon Deacons",
      "rank_delta_prev_minus_curr": 7,
      "top_driver": "athletic (up 0.00)"
    },
    {
      "player_name": "Antonio Williams",
      "position": "WR",
      "school": "Clemson Tigers",
      "rank_delta_prev_minus_curr": 7,
      "top_driver": "athletic (up 0.00)"
    },
    {
      "player_name": "Germie Bernard",
      "position": "WR",
      "school": "Alabama Crimson Tide",
      "rank_delta_prev_minus_curr": 6,
      "top_driver": "athletic (up 0.00)"
    },
    {
      "player_name": "Michael Trigg",
      "position": "TE",
      "school": "Baylor Bears",
      "rank_delta_prev_minus_curr": 6,
      "top_driver": "athletic (up 0.00)"
    },
    {
      "player_name": "Garrett Nussmeier",
      "position": "QB",
      "school": "LSU Tigers",
      "rank_delta_prev_minus_curr": 5,
      "top_driver": "athletic (up 0.00)"
    }
  ],
  "fallers": [
    {
      "player_name": "Tacario Davis",
      "position": "CB",
      "school": "Washington Huskies",
      "rank_delta_prev_minus_curr": -4,
      "top_driver": "guardrail_relief (down 0.22)"
    },
    {
      "player_name": "Reggie Virgil",
      "position": "WR",
      "school": "Texas Tech Red Raiders",
      "rank_delta_prev_minus_curr": -4,
      "top_driver": "athletic (up 0.00)"
    },
    {
      "player_name": "Xavian Sorey Jr.",
      "position": "LB",
      "school": "Arkansas Razorbacks",
      "rank_delta_prev_minus_curr": -4,
      "top_driver": "athletic (up 0.00)"
    },
    {
      "player_name": "Harold Perkins Jr.",
      "position": "LB",
      "school": "LSU Tigers",
      "rank_delta_prev_minus_curr": -3,
      "top_driver": "athletic (up 0.00)"
    },
    {
      "player_name": "Bud Clark",
      "position": "S",
      "school": "TCU Horned Frogs",
      "rank_delta_prev_minus_curr": -3,
      "top_driver": "guardrail_relief (down 0.36)"
    },
    {
      "player_name": "Mike Washington Jr.",
      "position": "RB",
      "school": "Arkansas Razorbacks",
      "rank_delta_prev_minus_curr": -3,
      "top_driver": "athletic (up 0.00)"
    },
    {
      "player_name": "Ted Hurst",
      "position": "WR",
      "school": "Georgia State Panthers",
      "rank_delta_prev_minus_curr": -3,
      "top_driver": "athletic (up 0.00)"
    },
    {
      "player_name": "Kaytron Allen",
      "position": "RB",
      "school": "Penn State Nittany Lions",
      "rank_delta_prev_minus_curr": -3,
      "top_driver": "guardrail_relief (down 0.36)"
    }
  ],
  "summary": {
    "movers_total": 188,
    "risers_total": 68,
    "fallers_total": 120,
    "qa_watch_total": 0,
    "qa_clear_total": 311
  }
}